tcutility/__init__.py
tcutility/cache.py
tcutility/cite.py
tcutility/connect.py
tcutility/constants.py
tcutility/environment.py
tcutility/errors.py
tcutility/formula.py
tcutility/geometry.py
tcutility/log.py
tcutility/molecule.py
tcutility/pathfunc.py
tcutility/slurm.py
tcutility/spell_check.py
tcutility/timer.py
tcutility/typing_utilities.py
tcutility/analysis/__init__.py
tcutility/analysis/pyfrag.py
tcutility/analysis/task_specific/__init__.py
tcutility/analysis/task_specific/irc.py
tcutility/analysis/vdd/__init__.py
tcutility/analysis/vdd/charge.py
tcutility/analysis/vdd/manager.py
tcutility/analysis/vibration/__init__.py
tcutility/analysis/vibration/ts_vibration.py
tcutility/cli_scripts/__init__.py
tcutility/cli_scripts/cite.py
tcutility/cli_scripts/concatenate_irc.py
tcutility/cli_scripts/geo.py
tcutility/cli_scripts/job_script.py
tcutility/cli_scripts/read.py
tcutility/cli_scripts/resize_figures.py
tcutility/cli_scripts/tcparser.py
tcutility/data/__init__.py
tcutility/data/_convert_to_json.py
tcutility/data/_read_BS_size.py
tcutility/data/atom.py
tcutility/data/available_functionals.json
tcutility/data/available_functionals.txt
tcutility/data/basis_sets.py
tcutility/data/cosmo.py
tcutility/data/functionals.py
tcutility/data/molecules.py
tcutility/data/_atom_data_info/__init__.py
tcutility/data/_atom_data_info/color.txt
tcutility/data/_atom_data_info/name.txt
tcutility/data/_atom_data_info/norbs.json
tcutility/data/_atom_data_info/radius.txt
tcutility/data/_atom_data_info/symbol.txt
tcutility/job/__init__.py
tcutility/job/adf.py
tcutility/job/ams.py
tcutility/job/crest.py
tcutility/job/dftb.py
tcutility/job/generic.py
tcutility/job/nmr.py
tcutility/job/orca.py
tcutility/job/xtb.py
tcutility/job/postscripts/__init__.py
tcutility/job/postscripts/clean_workdir.py
tcutility/job/postscripts/split_crest_xyz.py
tcutility/job/postscripts/write_converged_geoms.py
tcutility/report/__init__.py
tcutility/report/_char_widths.txt
tcutility/report/_generate_font_widths.py
tcutility-0.16.12.dist-info/licenses/LICENSE
tcutility-0.16.12.dist-info/METADATA
tcutility-0.16.12.dist-info/WHEEL
tcutility-0.16.12.dist-info/entry_points.txt
tcutility-0.16.12.dist-info/top_level.txt
tcutility-0.16.12.dist-info/RECORD
