Metadata-Version: 2.4
Name: TCutility
Version: 0.16.12
Summary: Utility package for working with AMS/ADF within the Theoretical Chemistry group at the Vrije Universiteit Amsterdam (TheoCheM). Makes use of plams - a package developed by SCM
Author: TheoCheM group
Maintainer: TheoCheM group
License: MIT
Classifier: Programming Language :: Python :: 3.8
Classifier: Programming Language :: Python :: 3.9
Classifier: Programming Language :: Python :: 3.10
Classifier: Programming Language :: Python :: 3.11
Classifier: Programming Language :: Python :: 3.12
Classifier: License :: OSI Approved :: MIT License
Classifier: Operating System :: OS Independent
Requires-Python: >=3.8
License-File: LICENSE
Requires-Dist: click>=8.1.8
Requires-Dist: dictfunc>=1.1.0
Requires-Dist: listfunc>=1.0.0
Requires-Dist: numpy>=1.24.4
Requires-Dist: plams>=2025.104
Requires-Dist: platformdirs>=4.3.6
Requires-Dist: requests>=2.32.4
Requires-Dist: strenum>=0.4.15
Provides-Extra: dev
Requires-Dist: gitpython>=3.1.45; extra == "dev"
Requires-Dist: pydata-sphinx-theme>=0.14.4; extra == "dev"
Requires-Dist: pytest>=8.3.5; extra == "dev"
Requires-Dist: pytest-cov>=5.0.0; extra == "dev"
Requires-Dist: ruff>=0.12.12; extra == "dev"
Requires-Dist: sphinx>=7.1.2; extra == "dev"
Requires-Dist: sphinx-autodoc-typehints>=2.0.1; extra == "dev"
Requires-Dist: sphinx-click>=6.0.0; extra == "dev"
Requires-Dist: sphinx-copybutton>=0.5.2; extra == "dev"
Requires-Dist: sphinx-tabs>=3.4.7; extra == "dev"
Requires-Dist: sphinxcontrib-applehelp>=1.0.4; extra == "dev"
Requires-Dist: sphinxcontrib-devhelp>=1.0.2; extra == "dev"
Requires-Dist: sphinxcontrib-htmlhelp>=2.0.1; extra == "dev"
Requires-Dist: sphinxcontrib-jsmath>=1.0.1; extra == "dev"
Requires-Dist: sphinxcontrib-qthelp>=1.0.3; extra == "dev"
Requires-Dist: sphinxcontrib-serializinghtml>=1.1.5; extra == "dev"
Provides-Extra: plot
Requires-Dist: matplotlib>=3.7.5; extra == "plot"
Provides-Extra: analysis
Requires-Dist: scipy>=1.10.1; extra == "analysis"
Provides-Extra: vdd
Requires-Dist: openpyxl>=3.1.5; extra == "vdd"
Requires-Dist: pandas>=2.0.3; extra == "vdd"
Provides-Extra: report
Requires-Dist: docx>=0.2.4; extra == "report"
Requires-Dist: htmldocx>=0.0.6; extra == "report"
Requires-Dist: opencv-python>=4.11.0.86; extra == "report"
Provides-Extra: connect
Requires-Dist: paramiko>=3.5.1; extra == "connect"
Dynamic: license-file
